nicegui_extentions/__init__.py
nicegui_extentions/markdown.py
nicegui_extentions/reconnect_box.py
nicegui_extentions-0.0.2.dist-info/LICENSE
nicegui_extentions-0.0.2.dist-info/METADATA
nicegui_extentions-0.0.2.dist-info/WHEEL
nicegui_extentions-0.0.2.dist-info/top_level.txt
nicegui_extentions-0.0.2.dist-info/RECORD
