Metadata-Version: 2.1
Name: nicegui_extentions
Version: 0.0.2
Summary: nicegui extensions
Author-email: T2XX <antongong@foxmail.com>
Project-URL: Homepage, https://github.com/T2XX/nicegui_extentions
Project-URL: Issues, https://github.com/T2XX/nicegui_extentions/issues
Classifier: Programming Language :: Python :: 3
Classifier: License :: OSI Approved :: MIT License
Classifier: Operating System :: OS Independent
Requires-Python: >=3.8
License-File: LICENSE
